luban/__init__.py
luban/fastapi_model.py
luban/shell_entrance.py
luban/data/mysql.json
fastapi_luban-0.1.2.dist-info/LICENSE
fastapi_luban-0.1.2.dist-info/METADATA
fastapi_luban-0.1.2.dist-info/WHEEL
fastapi_luban-0.1.2.dist-info/entry_points.txt
fastapi_luban-0.1.2.dist-info/top_level.txt
fastapi_luban-0.1.2.dist-info/zip-safe
fastapi_luban-0.1.2.dist-info/RECORD
